Workbook

Sheet 50 Products
A1: Rank/Priority | B1: Product name | C1: Category | D1: Diwali relevance | E1: Uniqueness angle | F1: Price band INR | G1: Source status | H1: Lead time class | I1: Sellability signal + source | J1: Notes | K1: Price Min INR | L1: Price Max INR
A2: 1 | B2: Carved Solid Sheesham Mandir / Temple Unit (2.5 ft) | C2: Mandir & Pooja Accessories | D2: Pooja-room centrepiece bought for Diwali/housewarming | E2: Solid carved wood vs mass engineered/laminate mandirs (Flipkart median ~INR 494, ESTIMATE) | F2: 14,999-16,999 | G2: stretch | H2: intricate | I2: Woodsala sells carved mandirs at INR 21,899 median (VERIFIED, India price benchmark Sec 3.1) - proven demand tier, zero live SKUs today | J2: Equivalent to S1 in superseded India starter-catalogue plan (spec reusable). URGENT: start carving decision needed by ~9-10 Oct, see markdown Sec 4 | K2: 14999 | L2: 16999
A3: 2 | B3: Hand-Carved Jharokha Mirror | C3: Wall Art, Mirrors & Frames | D3: Festival housewarming/entryway decor | E3: Rajasthani jharokha framing already Best Seller/Trending in the seed | F3: 11,900 | G3: catalogue | H3: standard | I3: Seed flags: Handmade, Best Seller, featured/best/trending | J3: slug hand-carved-jharokha-mirror, SKU WV-WAL-001; HERO pick #2 | K3: 11900 | L3: 11900
A4: 3 | B4: Jaali Carved Wall Panel | C4: Wall Art, Mirrors & Frames | D4: Photogenic statement wall piece, also usable as room divider | E4: Highest-margin item in the whole unit-economics model (24.5% after CAC) | F4: 10,400 | G4: catalogue | H4: standard | I4: unit-economics-model.md Sec 4 table B/C | J4: slug jaali-carved-wall-panel, SKU WV-WAL-002; HERO pick #3 | K4: 10400 | L4: 10400
A5: 4 | B5: Lacquered Lakshmi Figure (companion to item 21) | C5: Figurines & Idols (gifting) | D5: Completes the Lakshmi-Ganesha pair, the most-named Diwali idol gift | E5: Identical bow-lathe + friction-lacquer process; closes a named, searched pairing gap | F5: 4,790-5,200 solo; ~9,000-9,900 as a pair | G5: new SKU | H5: standard | I5: ESTIMATE - 'Laxmi-Ganesh idols thought to bring abundance' named as top Diwali gift (The Week, 13 Oct 2025) | J5: Genuinely new; HERO pick #4 (as pair with item 21) | K5: 4790 | L5: 5200
A6: 5 | B6: Hoshiarpur Inlay Serving Tray | C6: Serving Ware, Trays & Coasters | D6: Premium personal/corporate gifting tray | E6: Brass-inlay border differentiates vs plain acacia trays everywhere | F6: 5,290 | G6: catalogue | H6: standard | I6: Seed flags: Handmade, featured | J6: slug hoshiarpur-inlay-serving-tray, SKU WV-SRV-003; HERO pick #5 | K6: 5290 | L6: 5290
A7: 6 | B7: Hand-Carved Sheesham Door Toran with Brass Bells | C7: Torans & Door Decor | D7: Torans are THE top-cited Diwali purchase; ritual replacement every year | E7: Carved wood + real bells vs ubiquitous fabric/marigold/plastic torans | F7: 1,499-1,999 | G7: new SKU | H7: standard | I7: VERIFIED-signal / ESTIMATE-detail - "Torans are at the forefront of Diwali purchases" (Shiprocket, 'best selling products on Diwali', accessed 2026-10-06) | J7: Genuinely new; zero-SKU gap; HERO pick #6 | K7: 1499 | L7: 1999
A8: 7 | B8: Diwali Hamper - Premium (Inlay Tray + Lakshmi-Ganesha Pair + Mithai Box) | C8: Corporate & Personal Gift Hampers | D8: Premium personal/corporate tier research flags as the growing segment | E8: Combines three differentiated craft lines into one gift-box narrative | F8: 7,999-9,999 | G8: new SKU | H8: standard | I8: ESTIMATE - 'premium, memorable solutions, average spend rising' (vantagecircle.com, corporate Diwali gifts 2025) | J8: Genuinely new combo (components: items 26+21+22+34); HERO pick #7; decision 0037 combo engine | K8: 7999 | L8: 9999
A9: 8 | B9: Carved Wooden Elephant Pair | C9: Figurines & Idols (gifting) | D9: Good-luck prosperity gifting maps directly onto Diwali | E9: Already Best Seller + Trending; 'good luck' framing in seed copy | F9: 5,590 | G9: catalogue | H9: standard | I9: Seed flags: Handmade, Best Seller, best/trending | J9: slug carved-wooden-elephant-pair, SKU WV-FIG-002; HERO pick #8 | K9: 5590 | L9: 5590
A10: 9 | B10: Jaali Tealight Lantern, hanging sheesham | C10: Diyas & Candle Holders (wood-based) | D10: Wood-housed answer to the craft/customisation diya trend | E10: Hand-pierced jaali shadow pattern vs simpler turned-shape diya stands (Pepperfry, ESTIMATE) | F10: 899-1,299 | G10: new SKU | H10: standard | I10: ESTIMATE - Pepperfry festive-decor category sells a simpler 'wooden Om shadow tea light diya stand' (accessed 2026-10-06) | J10: Genuinely new; HERO pick #9 | K10: 899 | L10: 1299
A11: 10 | B11: Hoshiarpur Inlay Chess Set | C11: Kids & Toy Gifting | D11: Family-gathering gift for the Diwali long weekend | E11: Brass-inlaid border, turned Staunton pieces stored in hollow case | F11: 7,290 | G11: catalogue | H11: standard | I11: Seed flags: Handmade, featured | J11: slug hoshiarpur-inlay-chess-set, SKU WV-TOY-003; HERO pick #10 | K11: 7290 | L11: 7290
A12: 11 | B12: Sheesham Bajot / Chowki (Pooja-Idol Platform Stool) | C12: Mandir & Pooja Accessories | D12: Low wooden platform for idol/thali during Lakshmi puja | E12: Distinct from existing seating mudha - true pooja furniture, zero seed coverage | F12: 1,999-2,999 | G12: new SKU | H12: standard | I12: ASSUMPTION - pooja-corner buyers named as a segment (positioning-and-usp.md Sec 9.2) | J12: Genuinely new (not in starter-catalogue list) | K12: 1999 | L12: 2999
A13: 12 | B13: Panch-Diya Wooden Aarti Stand (5-cup brass + turned sheesham) | C13: Mandir & Pooja Accessories | D13: Daily aarti/diya stand used through the 5 days of Diwali | E13: Wood-housed reusable brass-cup design vs disposable clay diyas | F13: 1,499-1,999 | G13: new SKU | H13: standard | I13: ESTIMATE - "diyas are the heart of Diwali, trend is craft & customisation" (radhakrishnatemple.net, 2025, accessed 2026-10-06) | J13: Genuinely new | K13: 1499 | L13: 1999
... A51: 50 | B51: Corporate Bulk Gifting Set - Branded (Chess Set + Inlay Tray + branded card/plate) | C51: Corporate & Personal Gift Hampers | D51: B2B bulk occasion explicit in brief; personalisation/branding named as 2025-26 differentiator | E51: Engraved/branded corporate set vs unbranded generic hampers | F51: 6,999-8,999 /unit at bulk pricing | G51: stretch | H51: standard | I51: ESTIMATE - personalisation named as corporate differentiator (bombaysweetshop.com; enkash.com, accessed 2026-10-06) | J51: Needs engraving/branding capability + MOQ/lead-time check before any client quote (see markdown Sec 4, decision 2) | K51: 6999 | L51: 8999
A53: Legend:
A54: Hero pick (top 10)
A55: Catalogue (already seeded, re-merchandised)
A56: New SKU (buildable now)
A57: Stretch (capability check needed)

Sheet Hero Picks
A1: Rank | B1: Product name | C1: Category | D1: Price band INR | E1: Source status | F1: Why it's a hero
A2: 1 | B2: Carved Solid Sheesham Mandir / Temple Unit (2.5 ft) | C2: Mandir & Pooja Accessories | D2: 14,999-16,999 | E2: stretch | F2: Biggest white-space gap named in positioning doc; already costed as S1 in the starter-catalogue plan. STRETCH + URGENT decision (see Method sheet).
A3: 2 | B3: Hand-Carved Jharokha Mirror | C3: Wall Art, Mirrors & Frames | D3: 11,900 | E3: catalogue | F3: Already Best Seller + Trending in the seed; zero build work.
A4: 3 | B4: Jaali Carved Wall Panel | C4: Wall Art, Mirrors & Frames | D4: 10,400 | E4: catalogue | F4: Healthiest margin in the whole unit-economics model (24.5% after CAC).
A5: 4 | B5: Lacquered Lakshmi Figure (companion to item 21) | C5: Figurines & Idols (gifting) | D5: 4,790-5,200 solo; ~9,000-9,900 as a pair | E5: new SKU | F5: Completes the named, searched 'Laxmi-Ganesh' pair; one new SKU (Lakshmi) reuses an existing craft process.
A6: 5 | B6: Hoshiarpur Inlay Serving Tray | C6: Serving Ware, Trays & Coasters | D6: 5,290 | E6: catalogue | F6: Premium personal/corporate gifting tray; brass inlay vs mass acacia trays.
A7: 6 | B7: Hand-Carved Sheesham Door Toran with Brass Bells | C7: Torans & Door Decor | D7: 1,499-1,999 | E7: new SKU | F7: Torans are the #1-cited Diwali purchase category in research; currently a zero-SKU gap.
A8: 7 | B8: Diwali Hamper - Premium (Inlay Tray + Lakshmi-Ganesha Pair + Mithai Box) | C8: Corporate & Personal Gift Hampers | D8: 7,999-9,999 | E8: new SKU | F8: Corporate research flags personalised/craft hampers as the growing segment; built on the live combo engine (decision 0037).
A9: 8 | B9: Carved Wooden Elephant Pair | C9: Figurines & Idols (gifting) | D9: 5,590 | E9: catalogue | F9: Already Best Seller + Trending; 'good luck' prosperity framing fits Diwali with zero rework.
A10: 9 | B10: Jaali Tealight Lantern, hanging sheesham | C10: Diyas & Candle Holders (wood-based) | D10: 899-1,299 | E10: new SKU | F10: Wood-housed answer to the craft/customisation diya trend without becoming a generic clay diya.
A11: 10 | B11: Hoshiarpur Inlay Chess Set | C11: Kids & Toy Gifting | D11: 7,290 | E11: catalogue | F11: Family-gathering gift for the Diwali long weekend; zero new build work.

Sheet Category Summary
A1: Category | B1: Item count | C1: Catalogue count | D1: New SKU count | E1: Stretch count | F1: Min price band (INR) | G1: Max price band (INR) | H1: Avg of band midpoints (INR)
A2: Mandir & Pooja Accessories | B2: =COUNTIFS('50 Products'!$C$2:$C$51,$A2) -> 6 | C2: =COUNTIFS('50 Products'!$C$2:$C$51,$A2,'50 Products'!$G$2:$G$51,"catalogue") -> 0 | D2: =COUNTIFS('50 Products'!$C$2:$C$51,$A2,'50 Products'!$G$2:$G$51,"new SKU") -> 5 | E2: =COUNTIFS('50 Products'!$C$2:$C$51,$A2,'50 Products'!$G$2:$G$51,"stretch") -> 1 | F2: =_xlfn.MINIFS('50 Products'!$K$2:$K$51,'50 Products'!$C$2:$C$51,$A2) -> 399 | G2: =_xlfn.MAXIFS('50 Products'!$L$2:$L$51,'50 Products'!$C$2:$C$51,$A2) -> 16999 | H2: =AVERAGEIFS('50 Products'!$K$2:$K$51,'50 Products'!$C$2:$C$51,$A2)/2+AVERAGEIFS('50 Products'!$L$2:$L$51,'50 Products'!$C$2:$C$51,$A2)/2 -> 4140.6667
A3: Diyas & Candle Holders (wood-based) | B3: =COUNTIFS('50 Products'!$C$2:$C$51,$A3) -> 4 | C3: =COUNTIFS('50 Products'!$C$2:$C$51,$A3,'50 Products'!$G$2:$G$51,"catalogue") -> 0 | D3: =COUNTIFS('50 Products'!$C$2:$C$51,$A3,'50 Products'!$G$2:$G$51,"new SKU") -> 4 | E3: =COUNTIFS('50 Products'!$C$2:$C$51,$A3,'50 Products'!$G$2:$G$51,"stretch") -> 0 | F3: =_xlfn.MINIFS('50 Products'!$K$2:$K$51,'50 Products'!$C$2:$C$51,$A3) -> 899 | G3: =_xlfn.MAXIFS('50 Products'!$L$2:$L$51,'50 Products'!$C$2:$C$51,$A3) -> 2999 | H3: =AVERAGEIFS('50 Products'!$K$2:$K$51,'50 Products'!$C$2:$C$51,$A3)/2+AVERAGEIFS('50 Products'!$L$2:$L$51,'50 Products'!$C$2:$C$51,$A3)/2 -> 1786.5
A4: Torans & Door Decor | B4: =COUNTIFS('50 Products'!$C$2:$C$51,$A4) -> 4 | C4: =COUNTIFS('50 Products'!$C$2:$C$51,$A4,'50 Products'!$G$2:$G$51,"catalogue") -> 0 | D4: =COUNTIFS('50 Products'!$C$2:$C$51,$A4,'50 Products'!$G$2:$G$51,"new SKU") -> 4 | E4: =COUNTIFS('50 Products'!$C$2:$C$51,$A4,'50 Products'!$G$2:$G$51,"stretch") -> 0 | F4: =_xlfn.MINIFS('50 Products'!$K$2:$K$51,'50 Products'!$C$2:$C$51,$A4) -> 599 | G4: =_xlfn.MAXIFS('50 Products'!$L$2:$L$51,'50 Products'!$C$2:$C$51,$A4) -> 1999 | H4: =AVERAGEIFS('50 Products'!$K$2:$K$51,'50 Products'!$C$2:$C$51,$A4)/2+AVERAGEIFS('50 Products'!$L$2:$L$51,'50 Products'!$C$2:$C$51,$A4)/2 -> 1261.5
A5: Wall Art, Mirrors & Frames | B5: =COUNTIFS('50 Products'!$C$2:$C$51,$A5) -> 6 | C5: =COUNTIFS('50 Products'!$C$2:$C$51,$A5,'50 Products'!$G$2:$G$51,"catalogue") -> 5 | D5: =COUNTIFS('50 Products'!$C$2:$C$51,$A5,'50 Products'!$G$2:$G$51,"new SKU") -> 1 | E5: =COUNTIFS('50 Products'!$C$2:$C$51,$A5,'50 Products'!$G$2:$G$51,"stretch") -> 0 | F5: =_xlfn.MINIFS('50 Products'!$K$2:$K$51,'50 Products'!$C$2:$C$51,$A5) -> 699 | G5: =_xlfn.MAXIFS('50 Products'!$L$2:$L$51,'50 Products'!$C$2:$C$51,$A5) -> 11900 | H5: =AVERAGEIFS('50 Products'!$K$2:$K$51,'50 Products'!$C$2:$C$51,$A5)/2+AVERAGEIFS('50 Products'!$L$2:$L$51,'50 Products'!$C$2:$C$51,$A5)/2 -> 7794.8333
A6: Figurines & Idols (gifting) | B6: =COUNTIFS('50 Products'!$C$2:$C$51,$A6) -> 5 | C6: =COUNTIFS('50 Products'!$C$2:$C$51,$A6,'50 Products'!$G$2:$G$51,"catalogue") -> 4 | D6: =COUNTIFS('50 Products'!$C$2:$C$51,$A6,'50 Products'!$G$2:$G$51,"new SKU") -> 1 | E6: =COUNTIFS('50 Products'!$C$2:$C$51,$A6,'50 Products'!$G$2:$G$51,"stretch") -> 0 | F6: =_xlfn.MINIFS('50 Products'!$K$2:$K$51,'50 Products'!$C$2:$C$51,$A6) -> 4790 | G6: =_xlfn.MAXIFS('50 Products'!$L$2:$L$51,'50 Products'!$C$2:$C$51,$A6) -> 7900 | H6: =AVERAGEIFS('50 Products'!$K$2:$K$51,'50 Products'!$C$2:$C$51,$A6)/2+AVERAGEIFS('50 Products'!$L$2:$L$51,'50 Products'!$C$2:$C$51,$A6)/2 -> 6093
A7: Serving Ware, Trays & Coasters | B7: =COUNTIFS('50 Products'!$C$2:$C$51,$A7) -> 6 | C7: =COUNTIFS('50 Products'!$C$2:$C$51,$A7,'50 Products'!$G$2:$G$51,"catalogue") -> 4 | D7: =COUNTIFS('50 Products'!$C$2:$C$51,$A7,'50 Products'!$G$2:$G$51,"new SKU") -> 2 | E7: =COUNTIFS('50 Products'!$C$2:$C$51,$A7,'50 Products'!$G$2:$G$51,"stretch") -> 0 | F7: =_xlfn.MINIFS('50 Products'!$K$2:$K$51,'50 Products'!$C$2:$C$51,$A7) -> 299 | G7: =_xlfn.MAXIFS('50 Products'!$L$2:$L$51,'50 Products'!$C$2:$C$51,$A7) -> 5290 | H7: =AVERAGEIFS('50 Products'!$K$2:$K$51,'50 Products'!$C$2:$C$51,$A7)/2+AVERAGEIFS('50 Products'!$L$2:$L$51,'50 Products'!$C$2:$C$51,$A7)/2 -> 2288.8333
A8: Sweet / Dry-Fruit & Spice Boxes | B8: =COUNTIFS('50 Products'!$C$2:$C$51,$A8) -> 4 | C8: =COUNTIFS('50 Products'!$C$2:$C$51,$A8,'50 Products'!$G$2:$G$51,"catalogue") -> 3 | D8: =COUNTIFS('50 Products'!$C$2:$C$51,$A8,'50 Products'!$G$2:$G$51,"new SKU") -> 1 | E8: =COUNTIFS('50 Products'!$C$2:$C$51,$A8,'50 Products'!$G$2:$G$51,"stretch") -> 0 | F8: =_xlfn.MINIFS('50 Products'!$K$2:$K$51,'50 Products'!$C$2:$C$51,$A8) -> 1999 | G8: =_xlfn.MAXIFS('50 Products'!$L$2:$L$51,'50 Products'!$C$2:$C$51,$A8) -> 3590 | H8: =AVERAGEIFS('50 Products'!$K$2:$K$51,'50 Products'!$C$2:$C$51,$A8)/2+AVERAGEIFS('50 Products'!$L$2:$L$51,'50 Products'!$C$2:$C$51,$A8)/2 -> 2767.25
A9: Small Furniture Accents (festive refresh) | B9: =COUNTIFS('50 Products'!$C$2:$C$51,$A9) -> 5 | C9: =COUNTIFS('50 Products'!$C$2:$C$51,$A9,'50 Products'!$G$2:$G$51,"catalogue") -> 5 | D9: =COUNTIFS('50 Products'!$C$2:$C$51,$A9,'50 Products'!$G$2:$G$51,"new SKU") -> 0 | E9: =COUNTIFS('50 Products'!$C$2:$C$51,$A9,'50 Products'!$G$2:$G$51,"stretch") -> 0 | F9: =_xlfn.MINIFS('50 Products'!$K$2:$K$51,'50 Products'!$C$2:$C$51,$A9) -> 2990 | G9: =_xlfn.MAXIFS('50 Products'!$L$2:$L$51,'50 Products'!$C$2:$C$51,$A9) -> 16900 | H9: =AVERAGEIFS('50 Products'!$K$2:$K$51,'50 Products'!$C$2:$C$51,$A9)/2+AVERAGEIFS('50 Products'!$L$2:$L$51,'50 Products'!$C$2:$C$51,$A9)/2 -> 8836
A10: Kids & Toy Gifting | B10: =COUNTIFS('50 Products'!$C$2:$C$51,$A10) -> 3 | C10: =COUNTIFS('50 Products'!$C$2:$C$51,$A10,'50 Products'!$G$2:$G$51,"catalogue") -> 3 | D10: =COUNTIFS('50 Products'!$C$2:$C$51,$A10,'50 Products'!$G$2:$G$51,"new SKU") -> 0 | E10: =COUNTIFS('50 Products'!$C$2:$C$51,$A10,'50 Products'!$G$2:$G$51,"stretch") -> 0 | F10: =_xlfn.MINIFS('50 Products'!$K$2:$K$51,'50 Products'!$C$2:$C$51,$A10) -> 1090 | G10: =_xlfn.MAXIFS('50 Products'!$L$2:$L$51,'50 Products'!$C$2:$C$51,$A10) -> 7290 | H10: =AVERAGEIFS('50 Products'!$K$2:$K$51,'50 Products'!$C$2:$C$51,$A10)/2+AVERAGEIFS('50 Products'!$L$2:$L$51,'50 Products'!$C$2:$C$51,$A10)/2 -> 3790
A11: Lighting | B11: =COUNTIFS('50 Products'!$C$2:$C$51,$A11) -> 3 | C11: =COUNTIFS('50 Products'!$C$2:$C$51,$A11,'50 Products'!$G$2:$G$51,"catalogue") -> 3 | D11: =COUNTIFS('50 Products'!$C$2:$C$51,$A11,'50 Products'!$G$2:$G$51,"new SKU") -> 0 | E11: =COUNTIFS('50 Products'!$C$2:$C$51,$A11,'50 Products'!$G$2:$G$51,"stretch") -> 0 | F11: =_xlfn.MINIFS('50 Products'!$K$2:$K$51,'50 Products'!$C$2:$C$51,$A11) -> 3690 | G11: =_xlfn.MAXIFS('50 Products'!$L$2:$L$51,'50 Products'!$C$2:$C$51,$A11) -> 9790 | H11: =AVERAGEIFS('50 Products'!$K$2:$K$51,'50 Products'!$C$2:$C$51,$A11)/2+AVERAGEIFS('50 Products'!$L$2:$L$51,'50 Products'!$C$2:$C$51,$A11)/2 -> 6056.6667
A12: Corporate & Personal Gift Hampers | B12: =COUNTIFS('50 Products'!$C$2:$C$51,$A12) -> 4 | C12: =COUNTIFS('50 Products'!$C$2:$C$51,$A12,'50 Products'!$G$2:$G$51,"catalogue") -> 0 | D12: =COUNTIFS('50 Products'!$C$2:$C$51,$A12,'50 Products'!$G$2:$G$51,"new SKU") -> 3 | E12: =COUNTIFS('50 Products'!$C$2:$C$51,$A12,'50 Products'!$G$2:$G$51,"stretch") -> 1 | F12: =_xlfn.MINIFS('50 Products'!$K$2:$K$51,'50 Products'!$C$2:$C$51,$A12) -> 799 | G12: =_xlfn.MAXIFS('50 Products'!$L$2:$L$51,'50 Products'!$C$2:$C$51,$A12) -> 9999 | H12: =AVERAGEIFS('50 Products'!$K$2:$K$51,'50 Products'!$C$2:$C$51,$A12)/2+AVERAGEIFS('50 Products'!$L$2:$L$51,'50 Products'!$C$2:$C$51,$A12)/2 -> 5349
A13: TOTAL (all 50) | B13: =SUM(B2:B12) -> 50 | C13: =SUM(C2:C12) -> 27 | D13: =SUM(D2:D12) -> 21 | E13: =SUM(E2:E12) -> 2 | F13: =MIN(F2:F12) -> 299 | G13: =MAX(G2:G12) -> 16999
A15: Note: 'Min/Max price band' uses each item's lower/upper quoted price band; 'Avg of band midpoints' is the mean of (min+max)/2 across items in the category, used only to compare price-tier breadth across categories, not as a selling price.

Sheet Method & Caveats
A1: Method, sources and caveats
A3: Scope & date
A4: Built 2026-10-06 for The Wood Vintage's India-domestic Diwali 2026 push (Diwali = 8 Nov 2026, owner-stated; ~33 days of runway at time of writing). Navratri (11 Oct 2026) treated as a content-only warm-up window per docs/marketing/india-navratri-diwali-plan.md.
A6: Sources read
A7: Local DB was down at :5000 on 2026-10-06, so read backend/prisma/seed-data/catalogue.ts directly for the real 46-product seeded catalogue (all 'catalogue' rows cite the exact slug/SKU). Also read: docs/competitor-research/india-market-price-benchmark.md (196-row India price table), docs/competitor-research/india-competitor-analysis.md, docs/marketing/positioning-and-usp.md, docs/marketing/unit-economics-model.md, docs/marketing/first-100/03-starter-catalogue.md (superseded India starter-catalogue plan, S1-S16/Q1-Q4 - used to flag which 'new SKU' ideas were already planned vs genuinely new for Diwali), decisions 0028/0037/0039.
A9: Web research
A10: 4 targeted web searches run 2026-10-06 for genuine Diwali/festive-gifting demand signals in India 2026 (Amazon/Flipkart Diwali bestsellers, Pepperfry/Wooden Street festive collections, corporate gifting trend blogs, general Diwali decor trend blogs). Kept deliberately light per owner instruction ('be fast and decisive, do not over-research') - this is a demand-signal scan, not an exhaustive study.
A12: Evidence tags used inline
A13: VERIFIED = read live or in-repo 2026-10-06. ESTIMATE = search snippet/blog, undated or third-party, not independently re-verified. ASSUMPTION = our judgement, owner to confirm. No sales figures, review counts or 'bestseller' claims were invented for The Wood Vintage itself - every signal cites what a third-party source said about the category, never a fabricated claim about our own past sales (we have none; pre-launch).
A15: Source status definitions
A16: 'catalogue' = one of the 46 products already seeded in catalogue.ts (exact slug/SKU given in Notes) - Diwali relevance is a re-merchandising case, zero new build. 'new SKU' = not in the 46-product seed, buildable now with capability already demonstrated elsewhere in the catalogue (same craft, different form). 'stretch' = needs an explicit capability/capacity check (multi-panel carved doors for the mandir unit; engraving/branding for corporate bulk) before committing a ship date.
A18: Planning-doc flag
... A37: Full narrative version with all 50 items' complete relevance/uniqueness/signal write-ups, the skip/avoid section and the owner decision list lives at docs/marketing/diwali-2026/50-diwali-products.md - this workbook is the structured/sortable companion.
